scraper/__init__.py
scraper/game_info_scraper.py
scraper/game_time_scraper.py
scraper/live_stats_scraper.py
nba_scraping_api-0.0.2.dist-info/METADATA
nba_scraping_api-0.0.2.dist-info/WHEEL
nba_scraping_api-0.0.2.dist-info/top_level.txt
nba_scraping_api-0.0.2.dist-info/RECORD
